rsrssb/__init__.py
rsrssb/_version.py
rsrssb/episode.py
rsrssb/feed.py
rsrssb/main.py
rsrssb/myparser.py
rsrssb/tinytag.py
rsrssb/xmlwriter.py
rsrssb-0.2.3.post0.dist-info/METADATA
rsrssb-0.2.3.post0.dist-info/WHEEL
rsrssb-0.2.3.post0.dist-info/entry_points.txt
rsrssb-0.2.3.post0.dist-info/top_level.txt
rsrssb-0.2.3.post0.dist-info/RECORD
