Metadata-Version: 2.1
Name: rsrssb
Version: 0.2.3.post0
Summary: RSRSSB builds an RSS feed with arbitrary audio files.
Home-page: https://github.com/snowskeleton/rsrssb
Author: snowskeleton
Author-email: isaac@snowskeleton.net
License: Apache 2.0
Platform: UNKNOWN
Requires-Dist: ConfigArgParse
Requires-Dist: tinytag
Requires-Dist: toml
